HISTORY.rst
MANIFEST.in
README.rst
setup.py
ppadb/__init__.py
ppadb/application.py
ppadb/client.py
ppadb/connection.py
ppadb/device.py
ppadb/keycode.py
ppadb/protocol.py
ppadb/command/__init__.py
ppadb/command/host/__init__.py
ppadb/command/serial/__init__.py
ppadb/command/transport/__init__.py
ppadb/plugins/__init__.py
ppadb/plugins/client/__init__.py
ppadb/plugins/device/__init__.py
ppadb/plugins/device/batterystats.py
ppadb/plugins/device/batterystats_section.py
ppadb/plugins/device/cpustat.py
ppadb/plugins/device/input.py
ppadb/plugins/device/traffic.py
ppadb/plugins/device/utils.py
ppadb/plugins/device/wm.py
ppadb/sync/__init__.py
ppadb/sync/stats.py
ppadb/utils/__init__.py
ppadb/utils/logger.py
pure_python_adb.egg-info/PKG-INFO
pure_python_adb.egg-info/SOURCES.txt
pure_python_adb.egg-info/dependency_links.txt
pure_python_adb.egg-info/top_level.txt