Metadata-Version: 1.1
Name: pure-python-adb
Version: 0.2.6.dev0
Summary: Pure python implementation of the adb client
Home-page: https://github.com/Swind/pure-python-adb
Author: Swind Ou
Author-email: swind@cloudmosa.com
License: MIT license
Keywords: adb
Platform: UNKNOWN
Classifier: Development Status :: 4 - Beta
Classifier: Intended Audience :: Developers
Classifier: License :: OSI Approved :: MIT License
Classifier: Programming Language :: Python :: 3
Classifier: Programming Language :: Python :: 2.7
Classifier: Topic :: Software Development :: Testing
